{ "backgroundcolor":"#000000",
 "height":50,
 "infinite":false,
 "layers":[
        {
         "compression":"zlib",
         "data":"eJztlr0NwyAQRtkn+6TILBQMkDZVdsgQabxWjBKkk3Xm+Dkwwd8nPbkAzjwDthdj3PLFTE6S578lwXkKTy6S74yJ7ekZc7b19eF8Z87IvrZR3TP7jpRWvj5H+t4YfKzQXpPwPVIolR3Ox2MjbbWBb7\/AF77wrcuRvnt5Nqw9om+H\/w3X8BZZ8WvrTLs1hm957gpQX416gbP7aji\/BZwSXD2pfoimb858\/Tv48cMa+VnVPDOanutLKfUtoYfvlVDiK41P7RPzrXVOmYs15b7bfrm+W9eZfLdz2vOt8U49t6XnN7UfN6eYaymvta6EJVfqmzNWooUbx2W9l4QlV+qbM1ail2\/Ovtaklx8AAAAAAAAAAADG5QNeIFmL",
         "encoding":"base64",
         "height":50,
         "id":11,
         "name":"back",
         "opacity":0.5,
         "type":"tilelayer",
         "visible":true,
         "width":60,
         "x":0,
         "y":0
        }, 
        {
         "compression":"zlib",
         "data":"eJzt2EEOgjAQheEenAWXcMUBvAdLzwAX6UqbMAk2Q6y2dFr8v2RiIjrTJ1oV52DhYb0AoHF8RpCC9wnwzis1vmrabrXjV3TVXADQC+37xiccQ98m6wVURt5+yW\/jX6qF1yHsmZLh7j6veciYNST01+z\/f5QQ1jFH9912FT82Z07N52m80\/OeMbuFvNLvX\/J+e34tWJ7fGuQ6iVTYr3KvL65bD9mfW8krWeeo1kL9l11Pa0dZl8JzWsh7lPUM0ns0rhpZnTKnhTqTdbZaOQEAAAAAfXsCG4mnHQ==",
         "encoding":"base64",
         "height":50,
         "id":12,
         "name":"front",
         "opacity":1,
         "type":"tilelayer",
         "visible":true,
         "width":60,
         "x":0,
         "y":0
        }, 
        {
         "color":"#5555ff",
         "draworder":"topdown",
         "id":3,
         "name":"mods",
         "objects":[],
         "opacity":1,
         "type":"objectgroup",
         "visible":true,
         "x":0,
         "y":0
        }, 
        {
         "color":"#ff0000",
         "draworder":"topdown",
         "id":4,
         "name":"objects",
         "objects":[
                {
                 "gid":7376,
                 "height":16,
                 "id":819,
                 "name":"",
                 "properties":[
                        {
                         "name":"parameters",
                         "type":"string",
                         "value":"{\"treasurePools\":[\"valuableTreasure\"]}"
                        }],
                 "rotation":0,
                 "type":"",
                 "visible":true,
                 "width":24,
                 "x":168,
                 "y":256
                }, 
                {
                 "gid":7390,
                 "height":16,
                 "id":820,
                 "name":"",
                 "properties":[
                        {
                         "name":"parameters",
                         "type":"string",
                         "value":"{\"treasurePools\":[\"basicTreasure\"]}"
                        }],
                 "rotation":0,
                 "type":"",
                 "visible":true,
                 "width":24,
                 "x":288,
                 "y":256
                }, 
                {
                 "gid":7391,
                 "height":24,
                 "id":821,
                 "name":"",
                 "properties":[
                        {
                         "name":"parameters",
                         "type":"string",
                         "value":"{\"treasurePools\":[\"basicTreasure\"]}"
                        }],
                 "rotation":0,
                 "type":"",
                 "visible":true,
                 "width":24,
                 "x":320,
                 "y":256
                }, 
                {
                 "gid":5681,
                 "height":21,
                 "id":822,
                 "name":"",
                 "rotation":0,
                 "type":"",
                 "visible":true,
                 "width":40,
                 "x":128,
                 "y":184
                }, 
                {
                 "gid":5681,
                 "height":21,
                 "id":823,
                 "name":"",
                 "rotation":0,
                 "type":"",
                 "visible":true,
                 "width":40,
                 "x":432,
                 "y":184
                }, 
                {
                 "gid":5671,
                 "height":40,
                 "id":824,
                 "name":"",
                 "rotation":0,
                 "type":"",
                 "visible":true,
                 "width":40,
                 "x":200,
                 "y":256
                }, 
                {
                 "gid":5740,
                 "height":8,
                 "id":826,
                 "name":"",
                 "rotation":0,
                 "type":"",
                 "visible":true,
                 "width":40,
                 "x":408,
                 "y":192
                }, 
                {
                 "gid":2229,
                 "height":16,
                 "id":829,
                 "name":"",
                 "rotation":0,
                 "type":"",
                 "visible":true,
                 "width":16,
                 "x":240,
                 "y":240
                }, 
                {
                 "gid":6591,
                 "height":16,
                 "id":830,
                 "name":"",
                 "rotation":0,
                 "type":"",
                 "visible":true,
                 "width":16,
                 "x":240,
                 "y":216
                }, 
                {
                 "gid":6572,
                 "height":8,
                 "id":831,
                 "name":"",
                 "rotation":0,
                 "type":"",
                 "visible":true,
                 "width":10,
                 "x":176,
                 "y":208
                }, 
                {
                 "height":48,
                 "id":828,
                 "name":"",
                 "properties":[
                        {
                         "name":"stagehand",
                         "type":"string",
                         "value":"storageclue"
                        }],
                 "rotation":0,
                 "type":"",
                 "visible":true,
                 "width":80,
                 "x":280,
                 "y":216
                }, 
                {
                 "height":32,
                 "id":827,
                 "name":"",
                 "properties":[
                        {
                         "name":"stagehand",
                         "type":"string",
                         "value":"vaultitemspawn"
                        }],
                 "rotation":0,
                 "type":"",
                 "visible":true,
                 "width":40,
                 "x":160,
                 "y":232
                }, 
                {
                 "height":42.75,
                 "id":835,
                 "name":"",
                 "properties":[
                        {
                         "name":"stagehand",
                         "type":"string",
                         "value":"vaultnpcspawn"
                        }],
                 "rotation":0,
                 "type":"",
                 "visible":true,
                 "width":26.75,
                 "x":168.291666666667,
                 "y":214.458333333333
                }, 
                {
                 "gid":2924,
                 "height":40,
                 "id":837,
                 "name":"",
                 "rotation":0,
                 "type":"",
                 "visible":true,
                 "width":24,
                 "x":368,
                 "y":184
                }, 
                {
                 "gid":2911,
                 "height":16,
                 "id":839,
                 "name":"",
                 "properties":[
                        {
                         "name":"parameters",
                         "type":"string",
                         "value":"{\"treasurePools\":[\"basicTreasure\"]}"
                        }],
                 "rotation":0,
                 "type":"",
                 "visible":true,
                 "width":24,
                 "x":168,
                 "y":184
                }, 
                {
                 "gid":7048,
                 "height":16,
                 "id":840,
                 "name":"",
                 "rotation":0,
                 "type":"",
                 "visible":true,
                 "width":8,
                 "x":296,
                 "y":240
                }, 
                {
                 "gid":2856,
                 "height":20,
                 "id":841,
                 "name":"",
                 "rotation":0,
                 "type":"",
                 "visible":true,
                 "width":40,
                 "x":224,
                 "y":176
                }],
         "opacity":1,
         "type":"objectgroup",
         "visible":true,
         "x":0,
         "y":0
        }, 
        {
         "color":"#ffff00",
         "draworder":"topdown",
         "id":5,
         "name":"wiring - lights & guns",
         "objects":[],
         "opacity":1,
         "type":"objectgroup",
         "visible":true,
         "x":0,
         "y":0
        }, 
        {
         "color":"#ff0000",
         "draworder":"topdown",
         "id":6,
         "name":"monsters & npcs",
         "objects":[],
         "opacity":1,
         "type":"objectgroup",
         "visible":true,
         "x":0,
         "y":0
        }, 
        {
         "color":"#00ffff",
         "draworder":"topdown",
         "id":7,
         "name":"wiring - locked door",
         "objects":[
                {
                 "height":0,
                 "id":832,
                 "name":"",
                 "polyline":[
                        {
                         "x":0,
                         "y":0
                        }, 
                        {
                         "x":0,
                         "y":-24
                        }],
                 "rotation":0,
                 "type":"",
                 "visible":true,
                 "width":0,
                 "x":248,
                 "y":224
                }, 
                {
                 "height":0,
                 "id":833,
                 "name":"",
                 "polyline":[
                        {
                         "x":0,
                         "y":0
                        }, 
                        {
                         "x":-32,
                         "y":-8
                        }],
                 "rotation":0,
                 "type":"",
                 "visible":true,
                 "width":0,
                 "x":248,
                 "y":224
                }, 
                {
                 "height":0,
                 "id":834,
                 "name":"",
                 "polyline":[
                        {
                         "x":0,
                         "y":0
                        }, 
                        {
                         "x":-72,
                         "y":-24
                        }],
                 "rotation":0,
                 "type":"",
                 "visible":true,
                 "width":0,
                 "x":248,
                 "y":224
                }],
         "opacity":1,
         "type":"objectgroup",
         "visible":true,
         "x":0,
         "y":0
        }, 
        {
         "draworder":"topdown",
         "id":8,
         "name":"outside the map",
         "objects":[],
         "opacity":1,
         "type":"objectgroup",
         "visible":true,
         "x":0,
         "y":0
        }, 
        {
         "draworder":"topdown",
         "id":9,
         "name":"anchors etc",
         "objects":[],
         "opacity":1,
         "type":"objectgroup",
         "visible":true,
         "x":0,
         "y":0
        }, 
        {
         "draworder":"topdown",
         "id":10,
         "name":"items",
         "objects":[],
         "opacity":1,
         "type":"objectgroup",
         "visible":true,
         "x":0,
         "y":0
        }],
 "nextlayerid":13,
 "nextobjectid":842,
 "orientation":"orthogonal",
 "renderorder":"right-down",
 "tiledversion":"1.2.2",
 "tileheight":8,
 "tilesets":[
        {
         "firstgid":1,
         "source":"..\/..\/..\/tilesets\/packed\/materials.json"
        }, 
        {
         "firstgid":198,
         "source":"..\/..\/..\/tilesets\/packed\/miscellaneous.json"
        }, 
        {
         "firstgid":222,
         "source":"..\/..\/..\/tilesets\/packed\/liquids.json"
        }, 
        {
         "firstgid":250,
         "source":"..\/..\/..\/tilesets\/packed\/supports.json"
        }, 
        {
         "firstgid":287,
         "source":"..\/..\/..\/tilesets\/packed\/objects-by-race\/generic.json"
        }, 
        {
         "firstgid":2265,
         "source":"..\/..\/..\/tilesets\/packed\/objects-by-race\/ancient.json"
        }, 
        {
         "firstgid":2428,
         "source":"..\/..\/..\/tilesets\/packed\/objects-by-race\/apex.json"
        }, 
        {
         "firstgid":2799,
         "source":"..\/..\/..\/tilesets\/packed\/objects-by-race\/avian.json"
        }, 
        {
         "firstgid":3104,
         "source":"..\/..\/..\/tilesets\/packed\/objects-by-race\/floran.json"
        }, 
        {
         "firstgid":3299,
         "source":"..\/..\/..\/tilesets\/packed\/objects-by-race\/glitch.json"
        }, 
        {
         "firstgid":3525,
         "source":"..\/..\/..\/tilesets\/packed\/objects-by-race\/human.json"
        }, 
        {
         "firstgid":3812,
         "source":"..\/..\/..\/tilesets\/packed\/objects-by-race\/hylotl.json"
        }, 
        {
         "firstgid":4044,
         "source":"..\/..\/..\/tilesets\/packed\/objects-by-race\/novakid.json"
        }, 
        {
         "firstgid":4108,
         "source":"..\/..\/..\/tilesets\/packed\/objects-by-category\/crafting.json"
        }, 
        {
         "firstgid":4188,
         "source":"..\/..\/..\/tilesets\/packed\/objects-by-category\/decorative.json"
        }, 
        {
         "firstgid":5625,
         "source":"..\/..\/..\/tilesets\/packed\/objects-by-category\/door.json"
        }, 
        {
         "firstgid":5756,
         "source":"..\/..\/..\/tilesets\/packed\/objects-by-category\/farmable.json"
        }, 
        {
         "firstgid":5831,
         "source":"..\/..\/..\/tilesets\/packed\/objects-by-category\/furniture.json"
        }, 
        {
         "firstgid":6185,
         "source":"..\/..\/..\/tilesets\/packed\/objects-by-category\/light.json"
        }, 
        {
         "firstgid":6643,
         "source":"..\/..\/..\/tilesets\/packed\/objects-by-category\/other.json"
        }, 
        {
         "firstgid":6953,
         "source":"..\/..\/..\/tilesets\/packed\/objects-by-category\/pot.json"
        }, 
        {
         "firstgid":7250,
         "source":"..\/..\/..\/tilesets\/packed\/objects-by-category\/sapling.json"
        }, 
        {
         "firstgid":7251,
         "source":"..\/..\/..\/tilesets\/packed\/objects-by-category\/spawner.json"
        }, 
        {
         "firstgid":7267,
         "source":"..\/..\/..\/tilesets\/packed\/objects-by-category\/storage.json"
        }, 
        {
         "firstgid":7501,
         "source":"..\/..\/..\/tilesets\/packed\/objects-by-category\/teleporter.json"
        }, 
        {
         "firstgid":7543,
         "source":"..\/..\/..\/tilesets\/packed\/objects-by-category\/tools.json"
        }, 
        {
         "firstgid":7548,
         "source":"..\/..\/..\/tilesets\/packed\/objects-by-category\/trap.json"
        }, 
        {
         "firstgid":7752,
         "source":"..\/..\/..\/tilesets\/packed\/objects-by-category\/wire.json"
        }, 
        {
         "firstgid":7974,
         "source":"..\/..\/..\/tilesets\/packed\/objects-by-type\/container.json"
        }, 
        {
         "firstgid":8259,
         "source":"..\/..\/..\/tilesets\/packed\/objects-by-type\/farmable.json"
        }, 
        {
         "firstgid":8337,
         "source":"..\/..\/..\/tilesets\/packed\/objects-by-type\/loungeable.json"
        }, 
        {
         "firstgid":8618,
         "source":"..\/..\/..\/tilesets\/packed\/objects-by-type\/noisy.json"
        }, 
        {
         "firstgid":8659,
         "source":"..\/..\/..\/tilesets\/packed\/objects-by-type\/teleporter.json"
        }, 
        {
         "firstgid":8686,
         "source":"..\/..\/..\/tilesets\/packed\/huge-objects.json"
        }],
 "tilewidth":8,
 "type":"map",
 "version":1.2,
 "width":60
}