{ "backgroundcolor":"#000000",
 "height":60,
 "infinite":false,
 "layers":[
        {
         "compression":"zlib",
         "data":"eJzt2dsNwjAMBdCOwQ4sSecpnaN\/sBKtlEiRoQ\/HNnn4XumKDxS1p0WRRZZheCzoV4fK48G4Fy9OGk\/WGE\/WGHj7tcbA23c8WWPg7Tvw9h14bTKvvYXO1hc7CMc7Ckq93LVa4XjvglIvd61W4N0PvPDC2553Cp9PQamXu3ZK7kOSf84baUsF85VNWvNyZ0DteVLrWXG8JfdnutabN9f8T29arWdVs1f7\/XK9nP+fa\/Vy3Jwzldq9Z+6r56JTKHcG1J4nr67Ncf7qHNYePEKz5M6iudbS5y6SecObd4vUK5krrWZRTSP1SvZpq70d3jq88fc5Mr1ns2hvXm\/vt5R3qzevZK5MvZrzpKaP09d67St9k9LvS90\/vDrePXtLVg17y94cf+l7RFEURVHUph+U2tbA",
         "encoding":"base64",
         "height":60,
         "id":1,
         "name":"back",
         "opacity":0.5,
         "type":"tilelayer",
         "visible":true,
         "width":60,
         "x":0,
         "y":0
        }, 
        {
         "compression":"zlib",
         "data":"eJztmNltwzAMQNkNukcn9GeW6Aj9yyruSkWQCFUIHdTBQzIfQCABCMlPomxCAI7jOI7jOI7Dx4+RkEDbUdJZ201rn7+NhBR3IyHF7TXfTSnC3JJIrm+M+8rgvnvjvnvjvvvyBU\/fkV7w8+M9esY4JWSBpxfsGeMEGecZ\/WRqzNY4UXCh9c1PIeFsyTfA6W3R94FUffeA38+zsOzMwcPxF67jfMC\/c+y9K0f0+wrOB\/qPa7vFO+Rr30u29qLYt+aN86zdS1L7TopzKgffE866b5zdi4Zxw3Pj80z1PdF4I3D1LiXfnHOct5tv6r1dWpMVfXPOAPk6DnmaPTSlF835prwhk2PFl0LNF5\/f1N7HsaNvbv9nnl8uqL6B2ppc2Ve7v0wFl6\/1KPliar6rBMW15lv6hud6FM3A39sR35K7tmeLb8q5xWWWN6V+KHON+PY87yznkTWlIFlrHOP3sIJvqt656F3n3n0p+Y7saysza2oVruK5Kn8gskyi",
         "encoding":"base64",
         "height":60,
         "id":2,
         "name":"front",
         "opacity":1,
         "type":"tilelayer",
         "visible":true,
         "width":60,
         "x":0,
         "y":0
        }, 
        {
         "color":"#5555ff",
         "draworder":"topdown",
         "id":3,
         "name":"mods",
         "objects":[
                {
                 "height":48,
                 "id":824,
                 "name":"",
                 "properties":[
                        {
                         "name":"stagehand",
                         "type":"string",
                         "value":"npcspawn"
                        }],
                 "rotation":0,
                 "type":"",
                 "visible":true,
                 "width":88,
                 "x":96,
                 "y":152
                }, 
                {
                 "height":48,
                 "id":825,
                 "name":"",
                 "properties":[
                        {
                         "name":"stagehand",
                         "type":"string",
                         "value":"npcspawn"
                        }],
                 "rotation":0,
                 "type":"",
                 "visible":true,
                 "width":88,
                 "x":120,
                 "y":328
                }, 
                {
                 "height":48,
                 "id":826,
                 "name":"",
                 "properties":[
                        {
                         "name":"stagehand",
                         "type":"string",
                         "value":"npcspawn"
                        }],
                 "rotation":0,
                 "type":"",
                 "visible":true,
                 "width":88,
                 "x":272,
                 "y":328
                }, 
                {
                 "height":16,
                 "id":827,
                 "name":"",
                 "properties":[
                        {
                         "name":"stagehand",
                         "type":"string",
                         "value":"scanclue"
                        }],
                 "rotation":0,
                 "type":"",
                 "visible":true,
                 "width":16,
                 "x":256,
                 "y":264
                }, 
                {
                 "height":16,
                 "id":828,
                 "name":"",
                 "properties":[
                        {
                         "name":"stagehand",
                         "type":"string",
                         "value":"scanclue"
                        }],
                 "rotation":0,
                 "type":"",
                 "visible":true,
                 "width":16,
                 "x":136,
                 "y":336
                }, 
                {
                 "height":16,
                 "id":830,
                 "name":"",
                 "properties":[
                        {
                         "name":"stagehand",
                         "type":"string",
                         "value":"scanclue"
                        }],
                 "rotation":0,
                 "type":"",
                 "visible":true,
                 "width":16,
                 "x":144,
                 "y":160
                }, 
                {
                 "height":40,
                 "id":834,
                 "name":"",
                 "properties":[
                        {
                         "name":"stagehand",
                         "type":"string",
                         "value":"interactobject"
                        }],
                 "rotation":0,
                 "type":"",
                 "visible":true,
                 "width":40,
                 "x":352,
                 "y":344
                }],
         "opacity":1,
         "type":"objectgroup",
         "visible":true,
         "x":0,
         "y":0
        }, 
        {
         "color":"#ff0000",
         "draworder":"topdown",
         "id":4,
         "name":"objects",
         "objects":[
                {
                 "gid":2147489699,
                 "height":24,
                 "id":779,
                 "name":"",
                 "rotation":0,
                 "type":"",
                 "visible":true,
                 "width":16,
                 "x":160,
                 "y":288
                }, 
                {
                 "gid":3351,
                 "height":8,
                 "id":780,
                 "name":"",
                 "rotation":0,
                 "type":"",
                 "visible":true,
                 "width":16,
                 "x":136,
                 "y":272
                }, 
                {
                 "gid":2708,
                 "height":16,
                 "id":787,
                 "name":"",
                 "rotation":0,
                 "type":"",
                 "visible":true,
                 "width":8,
                 "x":128,
                 "y":272
                }, 
                {
                 "gid":5633,
                 "height":40,
                 "id":789,
                 "name":"",
                 "rotation":0,
                 "type":"",
                 "visible":true,
                 "width":40,
                 "x":56,
                 "y":288
                }, 
                {
                 "gid":3714,
                 "height":16,
                 "id":797,
                 "name":"",
                 "rotation":0,
                 "type":"",
                 "visible":true,
                 "width":24,
                 "x":264,
                 "y":360
                }, 
                {
                 "gid":2147490930,
                 "height":16,
                 "id":798,
                 "name":"",
                 "rotation":0,
                 "type":"",
                 "visible":true,
                 "width":24,
                 "x":256,
                 "y":376
                }, 
                {
                 "gid":7282,
                 "height":16,
                 "id":799,
                 "name":"",
                 "rotation":0,
                 "type":"",
                 "visible":true,
                 "width":24,
                 "x":280,
                 "y":376
                }, 
                {
                 "gid":2147490943,
                 "height":32,
                 "id":800,
                 "name":"",
                 "rotation":0,
                 "type":"",
                 "visible":true,
                 "width":16,
                 "x":304,
                 "y":288
                }, 
                {
                 "gid":2147490943,
                 "height":32,
                 "id":801,
                 "name":"",
                 "properties":[
                        {
                         "name":"parameters",
                         "type":"string",
                         "value":"{\"treasurePools\":[\"basicTreasure\"]}"
                        }],
                 "rotation":0,
                 "type":"",
                 "visible":true,
                 "width":16,
                 "x":328,
                 "y":288
                }, 
                {
                 "gid":6051,
                 "height":24,
                 "id":802,
                 "name":"",
                 "rotation":0,
                 "type":"",
                 "visible":true,
                 "width":16,
                 "x":112,
                 "y":288
                }, 
                {
                 "gid":5895,
                 "height":16,
                 "id":804,
                 "name":"",
                 "rotation":0,
                 "type":"",
                 "visible":true,
                 "width":32,
                 "x":128,
                 "y":288
                }, 
                {
                 "gid":2147490943,
                 "height":32,
                 "id":805,
                 "name":"",
                 "rotation":0,
                 "type":"",
                 "visible":true,
                 "width":16,
                 "x":352,
                 "y":288
                }, 
                {
                 "gid":5633,
                 "height":40,
                 "id":806,
                 "name":"",
                 "rotation":0,
                 "type":"",
                 "visible":true,
                 "width":40,
                 "x":304,
                 "y":200
                }, 
                {
                 "gid":5633,
                 "height":40,
                 "id":809,
                 "name":"",
                 "rotation":0,
                 "type":"",
                 "visible":true,
                 "width":40,
                 "x":208,
                 "y":376
                }, 
                {
                 "gid":3605,
                 "height":22,
                 "id":810,
                 "name":"",
                 "rotation":0,
                 "type":"",
                 "visible":true,
                 "width":19,
                 "x":104,
                 "y":376
                }, 
                {
                 "gid":2147486124,
                 "height":16,
                 "id":811,
                 "name":"",
                 "properties":[
                        {
                         "name":"parameters",
                         "type":"string",
                         "value":"{\"treasurePools\":[\"basicChestTreasure\"]}"
                        }],
                 "rotation":0,
                 "type":"",
                 "visible":true,
                 "width":16,
                 "x":192,
                 "y":336
                }, 
                {
                 "gid":2432,
                 "height":15,
                 "id":812,
                 "name":"",
                 "rotation":0,
                 "type":"",
                 "visible":true,
                 "width":16,
                 "x":152,
                 "y":376
                }, 
                {
                 "gid":2432,
                 "height":15,
                 "id":813,
                 "name":"",
                 "rotation":0,
                 "type":"",
                 "visible":true,
                 "width":16,
                 "x":168,
                 "y":376
                }, 
                {
                 "gid":3579,
                 "height":18,
                 "id":814,
                 "name":"",
                 "rotation":0,
                 "type":"",
                 "visible":true,
                 "width":48,
                 "x":112,
                 "y":200
                }, 
                {
                 "gid":3647,
                 "height":16,
                 "id":815,
                 "name":"",
                 "rotation":0,
                 "type":"",
                 "visible":true,
                 "width":24,
                 "x":80,
                 "y":200
                }, 
                {
                 "gid":5928,
                 "height":16,
                 "id":820,
                 "name":"",
                 "rotation":0,
                 "type":"",
                 "visible":true,
                 "width":16,
                 "x":176,
                 "y":200
                }, 
                {
                 "gid":2147491023,
                 "height":40,
                 "id":821,
                 "name":"",
                 "rotation":0,
                 "type":"",
                 "visible":true,
                 "width":32,
                 "x":272,
                 "y":200
                }, 
                {
                 "gid":2798,
                 "height":8,
                 "id":822,
                 "name":"",
                 "rotation":0,
                 "type":"",
                 "visible":true,
                 "width":8,
                 "x":176,
                 "y":184
                }, 
                {
                 "gid":2147491449,
                 "height":24,
                 "id":833,
                 "name":"",
                 "rotation":0,
                 "type":"",
                 "visible":true,
                 "width":24,
                 "x":360,
                 "y":376
                }, 
                {
                 "height":240,
                 "id":835,
                 "name":"",
                 "properties":[
                        {
                         "name":"stagehand",
                         "type":"string",
                         "value":"storageclue"
                        }],
                 "rotation":0,
                 "type":"",
                 "visible":true,
                 "width":192,
                 "x":184,
                 "y":144
                }, 
                {
                 "gid":6270,
                 "height":8,
                 "id":836,
                 "name":"",
                 "rotation":0,
                 "type":"",
                 "visible":true,
                 "width":16,
                 "x":144,
                 "y":320
                }, 
                {
                 "gid":6270,
                 "height":8,
                 "id":837,
                 "name":"",
                 "rotation":0,
                 "type":"",
                 "visible":true,
                 "width":16,
                 "x":304,
                 "y":320
                }, 
                {
                 "gid":6397,
                 "height":8,
                 "id":838,
                 "name":"",
                 "rotation":0,
                 "type":"",
                 "visible":true,
                 "width":16,
                 "x":208,
                 "y":144
                }, 
                {
                 "gid":6360,
                 "height":8,
                 "id":839,
                 "name":"",
                 "rotation":0,
                 "type":"",
                 "visible":true,
                 "width":24,
                 "x":128,
                 "y":232
                }, 
                {
                 "gid":6360,
                 "height":8,
                 "id":840,
                 "name":"",
                 "rotation":0,
                 "type":"",
                 "visible":true,
                 "width":24,
                 "x":272,
                 "y":232
                }],
         "opacity":1,
         "type":"objectgroup",
         "visible":true,
         "x":0,
         "y":0
        }, 
        {
         "color":"#ffff00",
         "draworder":"topdown",
         "id":5,
         "name":"wiring - lights & guns",
         "objects":[],
         "opacity":1,
         "type":"objectgroup",
         "visible":true,
         "x":0,
         "y":0
        }, 
        {
         "color":"#ff0000",
         "draworder":"topdown",
         "id":6,
         "name":"monsters & npcs",
         "objects":[],
         "opacity":1,
         "type":"objectgroup",
         "visible":true,
         "x":0,
         "y":0
        }, 
        {
         "color":"#00ffff",
         "draworder":"topdown",
         "id":7,
         "name":"wiring - locked door",
         "objects":[],
         "opacity":1,
         "type":"objectgroup",
         "visible":true,
         "x":0,
         "y":0
        }, 
        {
         "draworder":"topdown",
         "id":8,
         "name":"outside the map",
         "objects":[],
         "opacity":1,
         "type":"objectgroup",
         "visible":true,
         "x":0,
         "y":0
        }, 
        {
         "draworder":"topdown",
         "id":9,
         "name":"anchors etc",
         "objects":[
                {
                 "gid":202,
                 "height":8,
                 "id":708,
                 "name":"",
                 "rotation":0,
                 "type":"",
                 "visible":true,
                 "width":8,
                 "x":440,
                 "y":40
                }, 
                {
                 "gid":202,
                 "height":8,
                 "id":709,
                 "name":"",
                 "rotation":0,
                 "type":"",
                 "visible":true,
                 "width":8,
                 "x":240,
                 "y":16
                }, 
                {
                 "gid":202,
                 "height":8,
                 "id":710,
                 "name":"",
                 "rotation":0,
                 "type":"",
                 "visible":true,
                 "width":8,
                 "x":32,
                 "y":40
                }, 
                {
                 "gid":202,
                 "height":8,
                 "id":711,
                 "name":"",
                 "rotation":0,
                 "type":"",
                 "visible":true,
                 "width":8,
                 "x":8,
                 "y":264
                }, 
                {
                 "gid":202,
                 "height":8,
                 "id":712,
                 "name":"",
                 "rotation":0,
                 "type":"",
                 "visible":true,
                 "width":8,
                 "x":464,
                 "y":264
                }, 
                {
                 "gid":203,
                 "height":8,
                 "id":713,
                 "name":"",
                 "rotation":0,
                 "type":"",
                 "visible":true,
                 "width":8,
                 "x":440,
                 "y":328
                }, 
                {
                 "gid":203,
                 "height":8,
                 "id":714,
                 "name":"",
                 "rotation":0,
                 "type":"",
                 "visible":true,
                 "width":8,
                 "x":40,
                 "y":328
                }, 
                {
                 "gid":214,
                 "height":8,
                 "id":750,
                 "name":"",
                 "rotation":0,
                 "type":"",
                 "visible":true,
                 "width":8,
                 "x":440,
                 "y":40
                }, 
                {
                 "gid":214,
                 "height":8,
                 "id":751,
                 "name":"",
                 "rotation":0,
                 "type":"",
                 "visible":true,
                 "width":8,
                 "x":240,
                 "y":16
                }, 
                {
                 "gid":214,
                 "height":8,
                 "id":752,
                 "name":"",
                 "rotation":0,
                 "type":"",
                 "visible":true,
                 "width":8,
                 "x":32,
                 "y":40
                }, 
                {
                 "gid":214,
                 "height":8,
                 "id":754,
                 "name":"",
                 "rotation":0,
                 "type":"",
                 "visible":true,
                 "width":8,
                 "x":8,
                 "y":264
                }, 
                {
                 "gid":214,
                 "height":8,
                 "id":755,
                 "name":"",
                 "rotation":0,
                 "type":"",
                 "visible":true,
                 "width":8,
                 "x":464,
                 "y":264
                }],
         "opacity":1,
         "type":"objectgroup",
         "visible":true,
         "x":0,
         "y":0
        }, 
        {
         "draworder":"topdown",
         "id":10,
         "name":"items",
         "objects":[],
         "opacity":1,
         "type":"objectgroup",
         "visible":true,
         "x":0,
         "y":0
        }],
 "nextlayerid":11,
 "nextobjectid":842,
 "orientation":"orthogonal",
 "renderorder":"right-down",
 "tiledversion":"1.2.2",
 "tileheight":8,
 "tilesets":[
        {
         "firstgid":1,
         "source":"..\/..\/..\/tilesets\/packed\/materials.json"
        }, 
        {
         "firstgid":198,
         "source":"..\/..\/..\/tilesets\/packed\/miscellaneous.json"
        }, 
        {
         "firstgid":222,
         "source":"..\/..\/..\/tilesets\/packed\/liquids.json"
        }, 
        {
         "firstgid":250,
         "source":"..\/..\/..\/tilesets\/packed\/supports.json"
        }, 
        {
         "firstgid":287,
         "source":"..\/..\/..\/tilesets\/packed\/objects-by-race\/generic.json"
        }, 
        {
         "firstgid":2267,
         "source":"..\/..\/..\/tilesets\/packed\/objects-by-race\/ancient.json"
        }, 
        {
         "firstgid":2430,
         "source":"..\/..\/..\/tilesets\/packed\/objects-by-race\/apex.json"
        }, 
        {
         "firstgid":2801,
         "source":"..\/..\/..\/tilesets\/packed\/objects-by-race\/avian.json"
        }, 
        {
         "firstgid":3106,
         "source":"..\/..\/..\/tilesets\/packed\/objects-by-race\/floran.json"
        }, 
        {
         "firstgid":3301,
         "source":"..\/..\/..\/tilesets\/packed\/objects-by-race\/glitch.json"
        }, 
        {
         "firstgid":3527,
         "source":"..\/..\/..\/tilesets\/packed\/objects-by-race\/human.json"
        }, 
        {
         "firstgid":3814,
         "source":"..\/..\/..\/tilesets\/packed\/objects-by-race\/hylotl.json"
        }, 
        {
         "firstgid":4046,
         "source":"..\/..\/..\/tilesets\/packed\/objects-by-race\/novakid.json"
        }, 
        {
         "firstgid":4110,
         "source":"..\/..\/..\/tilesets\/packed\/objects-by-category\/crafting.json"
        }, 
        {
         "firstgid":4190,
         "source":"..\/..\/..\/tilesets\/packed\/objects-by-category\/decorative.json"
        }, 
        {
         "firstgid":5627,
         "source":"..\/..\/..\/tilesets\/packed\/objects-by-category\/door.json"
        }, 
        {
         "firstgid":5758,
         "source":"..\/..\/..\/tilesets\/packed\/objects-by-category\/farmable.json"
        }, 
        {
         "firstgid":5833,
         "source":"..\/..\/..\/tilesets\/packed\/objects-by-category\/furniture.json"
        }, 
        {
         "firstgid":6187,
         "source":"..\/..\/..\/tilesets\/packed\/objects-by-category\/light.json"
        }, 
        {
         "firstgid":6645,
         "source":"..\/..\/..\/tilesets\/packed\/objects-by-category\/other.json"
        }, 
        {
         "firstgid":6957,
         "source":"..\/..\/..\/tilesets\/packed\/objects-by-category\/pot.json"
        }, 
        {
         "firstgid":7254,
         "source":"..\/..\/..\/tilesets\/packed\/objects-by-category\/sapling.json"
        }, 
        {
         "firstgid":7255,
         "source":"..\/..\/..\/tilesets\/packed\/objects-by-category\/spawner.json"
        }, 
        {
         "firstgid":7271,
         "source":"..\/..\/..\/tilesets\/packed\/objects-by-category\/storage.json"
        }, 
        {
         "firstgid":7505,
         "source":"..\/..\/..\/tilesets\/packed\/objects-by-category\/teleporter.json"
        }, 
        {
         "firstgid":7547,
         "source":"..\/..\/..\/tilesets\/packed\/objects-by-category\/tools.json"
        }, 
        {
         "firstgid":7552,
         "source":"..\/..\/..\/tilesets\/packed\/objects-by-category\/trap.json"
        }, 
        {
         "firstgid":7756,
         "source":"..\/..\/..\/tilesets\/packed\/objects-by-category\/wire.json"
        }, 
        {
         "firstgid":7978,
         "source":"..\/..\/..\/tilesets\/packed\/objects-by-type\/container.json"
        }, 
        {
         "firstgid":8263,
         "source":"..\/..\/..\/tilesets\/packed\/objects-by-type\/farmable.json"
        }, 
        {
         "firstgid":8341,
         "source":"..\/..\/..\/tilesets\/packed\/objects-by-type\/loungeable.json"
        }, 
        {
         "firstgid":8622,
         "source":"..\/..\/..\/tilesets\/packed\/objects-by-type\/noisy.json"
        }, 
        {
         "firstgid":8663,
         "source":"..\/..\/..\/tilesets\/packed\/objects-by-type\/teleporter.json"
        }, 
        {
         "firstgid":8690,
         "source":"..\/..\/..\/tilesets\/packed\/huge-objects.json"
        }],
 "tilewidth":8,
 "type":"map",
 "version":1.2,
 "width":60
}